y_scramble/__init__.py
y_scramble/plots.py
y_scramble/scramble.py
y_scramble-0.0.8.dist-info/METADATA
y_scramble-0.0.8.dist-info/WHEEL
y_scramble-0.0.8.dist-info/top_level.txt
y_scramble-0.0.8.dist-info/RECORD
