Metadata-Version: 2.1
Name: y-scramble
Version: 0.0.8
Summary: Y-Scramble: a package for y-randomization validation
Author: Frederico Schmitt Kremer
Author-email: fred.s.kremer@gmail.com
License: UNKNOWN
Keywords: machine learnings qsar data science
Platform: UNKNOWN
Requires-Dist: pandas
Requires-Dist: numpy
Requires-Dist: scipy
Requires-Dist: scikit-learn
Requires-Dist: pytest
Requires-Dist: tqdm
